consts/__init__.py
consts/endpoint.py
consts/host.py
test/__init__.py
test/client_test.py
zuorapy/__init__.py
zuorapy/client.py
zuorapy-0.0.4.dist-info/METADATA
zuorapy-0.0.4.dist-info/RECORD
zuorapy-0.0.4.dist-info/WHEEL
zuorapy-0.0.4.dist-info/top_level.txt
