Metadata-Version: 2.1
Name: zuorapy
Version: 0.0.4
Summary: Zuora Rest Client for Python
Home-page: https://bitbucket.org/ihong5/zuorapy
Author: ihong5
Author-email: ihong3589@gmail.com
License: UNKNOWN
Platform: UNKNOWN
Classifier: Programming Language :: Python :: 3
Classifier: License :: OSI Approved :: MIT License
Classifier: Operating System :: OS Independent
